[
    {
        "id": "4030ddff-b4cb-4cb2-aad0-86989cee68ee",
        "type": "Home",
        "name": "Home",
        "address": "69 W 33RD ST, READING, PA, 19606",
        "addressLine1": "69 W 33RD ST",
        "addressLine2": null,
        "city": "READING",
        "state": "Pennsylvania",
        "stateCode": "PA",
        "zip": "19606",
        "country": "UNITED STATES OF AMERICA",
        "countryCode": "US",
        "phone": "",
        "isDefault": false,
        "isAddressMatched": false,
        "latitude": 40.3201432,
        "longitude": -75.878489,
        "firstName": "MARISA",
        "lastName": "BERNHEISER",
        "email": null,
        "customAddressType": null,
        "isDmvVerified": true
    },
    {
        "id": "cb691460-b1cc-484e-8979-536c4ece9569",
        "type": "Home",
        "name": "test",
        "address": "test",
        "addressLine1": "test",
        "addressLine2": "test",
        "city": "Mount Penn",
        "state": "Pennsylvania",
        "stateCode": null,
        "zip": "19606",
        "country": "United States",
        "countryCode": "US",
        "phone": "11111111111",
        "isDefault": false,
        "isAddressMatched": false,
        "latitude": 0,
        "longitude": 0,
        "firstName": "test",
        "lastName": "test",
        "email": "test@gmail.com",
        "customAddressType": null,
        "isDmvVerified": false
    }
]